{
    "userLoggedIn": false,
    "loggedInUserDetails": {
        "EMAILADDRESS": "",
        "FIRSTNAME": "",
        "LASTNAME": "",
        "PASSWORDHASH": "",
        "PASSWORDSALT": ""
    },
    "register": {
        "EMAILADDRESS": "",
        "FIRSTNAME": "",
        "LASTNAME": "",
        "PASSWORDHASH": "",
        "PASSWORDSALT": ""
    },
    "balance": {
        "debts": [
            {
                "DEBTOR": "",
                "GROSS": 0
            }
        ],
        "credits": [
            {
                "CREDITOR": "",
                "GROSS": 0
            }
        ]
    },
    "payday": {
        "SelectedUsers": [
            {
                "EMAILADDRESS": "",
                "FIRSTNAME": "",
                "LASTNAME": ""
            },
            {
                "EMAILADDRESS": "",
                "FIRSTNAME": "",
                "LASTNAME": ""
            },
            {
                "EMAILADDRESS": "",
                "FIRSTNAME": "",
                "LASTNAME": ""
            }
        ],
        "Transaction": [
            {
                "CREDITOR": "",
                "GROSS": 0,
                "DEBTOR": "",
                "REFERENCE": "",
                "DATE": ""
            },
            {
                "CREDITOR": "",
                "GROSS": 0,
                "DEBTOR": "",
                "REFERENCE": "",
                "DATE": ""
            },
            {
                "CREDITOR": "",
                "GROSS": 0,
                "DEBTOR": "",
                "REFERENCE": "",
                "DATE": ""
            }
        ]
    },
    "stacks": {
        "gridObj": {}
    },
    "history": [
        {
            "historicTransactions": {
                "CREDITOR": "",
                "GROSS": 0,
                "DEBTOR": "",
                "REFERENCE": "",
                "DATE": ""
            }
        }
    ],
    "details": {
        "userInfo": {
            "EMAILADDRESS": "",
            "FIRSTNAME": "",
            "LASTNAME": ""
        },
        "changePassword": false,
        "deleteUser": false
    }
}